pitapy/__init__.py
pitapy/pita.py
pitapy/base/__init__.py
pitapy/base/assembler.py
pitapy/base/asset_parsing/__init__.py
pitapy/base/asset_parsing/blueprint_manager.py
pitapy/base/asset_parsing/mujoco_loader.py
pitapy/base/asset_parsing/mujoco_object.py
pitapy/base/asset_parsing/parser.py
pitapy/base/asset_placement/__init__.py
pitapy/base/asset_placement/layout_manager.py
pitapy/base/asset_placement/validator.py
pitapy/base/asset_placement/distributions/__init__.py
pitapy/base/asset_placement/distributions/abstract_placer_distribution.py
pitapy/base/asset_placement/distributions/distribution_collection.py
pitapy/base/asset_placement/placer/__init__.py
pitapy/base/asset_placement/placer/abstract_placer.py
pitapy/base/asset_placement/placer/border_placer.py
pitapy/base/asset_placement/placer/fixed_placer.py
pitapy/base/asset_placement/placer/object_placer.py
pitapy/base/asset_placement/placer/random_placer.py
pitapy/base/asset_placement/rules/__init__.py
pitapy/base/asset_placement/rules/abstract_rule.py
pitapy/base/asset_placement/rules/boundary_rule.py
pitapy/base/asset_placement/rules/height_rule.py
pitapy/base/asset_placement/rules/min_distance_mujoco_physics_rule.py
pitapy/base/asset_placement/rules/min_distance_rule.py
pitapy/base/asset_placement/rules/rule_assembler.py
pitapy/base/asset_placement/rules/user_config_rule.py
pitapy/base/world_sites/__init__.py
pitapy/base/world_sites/abstract_site.py
pitapy/base/world_sites/area.py
pitapy/base/world_sites/environment.py
pitapy/examples/config_files/ballpit.yml
pitapy/examples/config_files/complex-config.yml
pitapy/examples/config_files/simple-config.yml
pitapy/examples/xml_objects/Agent.xml
pitapy/examples/xml_objects/Apple.xml
pitapy/examples/xml_objects/Ball.xml
pitapy/examples/xml_objects/Border.xml
pitapy/examples/xml_objects/BoxAgent.xml
pitapy/examples/xml_objects/Stone.xml
pitapy/examples/xml_objects/Tree.xml
pitapy/examples/xml_objects/Tree01.xml
pitapy/examples/xml_objects/Tree02.xml
pitapy-1.0.2.dist-info/LICENSE
pitapy-1.0.2.dist-info/METADATA
pitapy-1.0.2.dist-info/WHEEL
pitapy-1.0.2.dist-info/top_level.txt
pitapy-1.0.2.dist-info/RECORD
