Metadata-Version: 2.1
Name: pitapy
Version: 1.0.2
Summary: Update dependencies in requirements.txt, specifying webcolors 1.13
Author: MicrocosmAI
License: BSD-3-Clause
Project-URL: Source Code, https://github.com/microcosmAI/pita/
Project-URL: Documentation, https://github.com/microcosmAI/pita/tree/develop/docs/
Project-URL: Bug Tracker, https://github.com/microcosmAI/pita/issues/
Keywords: reinforcement learning,rl,multi agent reinforcement learning,marl,randomized world generation,mujoco,research,procedural iterative terrain assembly,dm_control
Classifier: Programming Language :: Python :: 3
Classifier: License :: OSI Approved :: BSD License
Classifier: Operating System :: OS Independent
Classifier: Intended Audience :: Science/Research
Classifier: Intended Audience :: Developers
Requires-Python: >=3.9
License-File: LICENSE
Requires-Dist: pyyaml
Requires-Dist: dm_control
Requires-Dist: shapely
Requires-Dist: matplotlib
Requires-Dist: sphinx
Requires-Dist: karma-sphinx-theme
Requires-Dist: webcolors
Requires-Dist: pillow
Requires-Dist: typer
